<annotation>
	<folder />
	<filename>12662155_18322524_jpeg.rf.696b6d241a4ed5ef47af5b61b12c8951.jpg</filename>
	<path>12662155_18322524_jpeg.rf.696b6d241a4ed5ef47af5b61b12c8951.jpg</path>
	<source>
		<database>roboflow.com</database>
	</source>
	<size>
		<width>768</width>
		<height>1024</height>
		<depth>3</depth>
	</size>
	<segmented>0</segmented>
	<object>
		<name>ladybug</name>
		<pose>Unspecified</pose>
		<truncated>0</truncated>
		<difficult>0</difficult>
		<bndbox>
			<xmin>394</xmin>
			<ymin>664</ymin>
			<xmax>501</xmax>
			<ymax>734</ymax>
		</bndbox>
	</object>
</annotation>