<annotation>
	<folder />
	<filename>296_4_army_worm-56-_jpg.rf.36ebbd358f3aab92a82156752c6d9a46.jpg</filename>
	<path>296_4_army_worm-56-_jpg.rf.36ebbd358f3aab92a82156752c6d9a46.jpg</path>
	<source>
		<database>roboflow.com</database>
	</source>
	<size>
		<width>640</width>
		<height>640</height>
		<depth>3</depth>
	</size>
	<segmented>0</segmented>
	<object>
		<name>army worm</name>
		<pose>Unspecified</pose>
		<truncated>0</truncated>
		<difficult>0</difficult>
		<bndbox>
			<xmin>134</xmin>
			<ymin>215</ymin>
			<xmax>564</xmax>
			<ymax>521</ymax>
		</bndbox>
	</object>
</annotation>