<annotation>
	<folder />
	<filename>29786995_46506058_jpg.rf.b63e6e74e37bf7febe90221c5888dc49.jpg</filename>
	<path>29786995_46506058_jpg.rf.b63e6e74e37bf7febe90221c5888dc49.jpg</path>
	<source>
		<database>roboflow.com</database>
	</source>
	<size>
		<width>768</width>
		<height>1024</height>
		<depth>3</depth>
	</size>
	<segmented>0</segmented>
	<object>
		<name>ladybug</name>
		<pose>Unspecified</pose>
		<truncated>0</truncated>
		<difficult>0</difficult>
		<bndbox>
			<xmin>355</xmin>
			<ymin>678</ymin>
			<xmax>405</xmax>
			<ymax>737</ymax>
		</bndbox>
	</object>
</annotation>