<annotation>
	<folder />
	<filename>458_3_army_worm-31-_jpg.rf.3704035496d455de67bae9edda61f96c.jpg</filename>
	<path>458_3_army_worm-31-_jpg.rf.3704035496d455de67bae9edda61f96c.jpg</path>
	<source>
		<database>roboflow.com</database>
	</source>
	<size>
		<width>640</width>
		<height>640</height>
		<depth>3</depth>
	</size>
	<segmented>0</segmented>
	<object>
		<name>army worm</name>
		<pose>Unspecified</pose>
		<truncated>0</truncated>
		<difficult>0</difficult>
		<bndbox>
			<xmin>309</xmin>
			<ymin>250</ymin>
			<xmax>508</xmax>
			<ymax>511</ymax>
		</bndbox>
	</object>
</annotation>