<annotation>
	<folder />
	<filename>554_3_army_worm-22-_jpg.rf.6d79ca10f4f25ff689142a9a12e6361f.jpg</filename>
	<path>554_3_army_worm-22-_jpg.rf.6d79ca10f4f25ff689142a9a12e6361f.jpg</path>
	<source>
		<database>roboflow.com</database>
	</source>
	<size>
		<width>640</width>
		<height>640</height>
		<depth>3</depth>
	</size>
	<segmented>0</segmented>
	<object>
		<name>army worm</name>
		<pose>Unspecified</pose>
		<truncated>0</truncated>
		<difficult>0</difficult>
		<bndbox>
			<xmin>209</xmin>
			<ymin>304</ymin>
			<xmax>507</xmax>
			<ymax>456</ymax>
		</bndbox>
	</object>
</annotation>