<annotation>
	<folder />
	<filename>758_jpg.rf.1ff7e825939834744367c1c983207e60.jpg</filename>
	<path>758_jpg.rf.1ff7e825939834744367c1c983207e60.jpg</path>
	<source>
		<database>roboflow.com</database>
	</source>
	<size>
		<width>300</width>
		<height>300</height>
		<depth>3</depth>
	</size>
	<segmented>0</segmented>
	<object>
		<name>locust</name>
		<pose>Unspecified</pose>
		<truncated>0</truncated>
		<difficult>0</difficult>
		<bndbox>
			<xmin>38</xmin>
			<ymin>74</ymin>
			<xmax>244</xmax>
			<ymax>216</ymax>
		</bndbox>
	</object>
</annotation>