<annotation>
	<folder />
	<filename>86_2_Black_Cutworm-16-_jpg.rf.08f2ca10ca6879b84704b608b7d84635.jpg</filename>
	<path>86_2_Black_Cutworm-16-_jpg.rf.08f2ca10ca6879b84704b608b7d84635.jpg</path>
	<source>
		<database>roboflow.com</database>
	</source>
	<size>
		<width>640</width>
		<height>640</height>
		<depth>3</depth>
	</size>
	<segmented>0</segmented>
	<object>
		<name>black cutworm</name>
		<pose>Unspecified</pose>
		<truncated>0</truncated>
		<difficult>0</difficult>
		<bndbox>
			<xmin>110</xmin>
			<ymin>43</ymin>
			<xmax>457</xmax>
			<ymax>588</ymax>
		</bndbox>
	</object>
</annotation>