<annotation>
	<folder />
	<filename>Fall-armyworms_134_jpeg-Copy_jpg.rf.7e13c9d195f714bdc84433fe5ef5c2a9.jpg</filename>
	<path>Fall-armyworms_134_jpeg-Copy_jpg.rf.7e13c9d195f714bdc84433fe5ef5c2a9.jpg</path>
	<source>
		<database>roboflow.com</database>
	</source>
	<size>
		<width>640</width>
		<height>640</height>
		<depth>3</depth>
	</size>
	<segmented>0</segmented>
	<object>
		<name>army worm</name>
		<pose>Unspecified</pose>
		<truncated>0</truncated>
		<difficult>0</difficult>
		<bndbox>
			<xmin>278</xmin>
			<ymin>171</ymin>
			<xmax>585</xmax>
			<ymax>335</ymax>
		</bndbox>
	</object>
</annotation>