<annotation>
	<folder />
	<filename>IP024002032_jpg.rf.9344fddd52f8b5500c0527bde1c7d60e.jpg</filename>
	<path>IP024002032_jpg.rf.9344fddd52f8b5500c0527bde1c7d60e.jpg</path>
	<source>
		<database>roboflow.com</database>
	</source>
	<size>
		<width>640</width>
		<height>640</height>
		<depth>3</depth>
	</size>
	<segmented>0</segmented>
	<object>
		<name>Aphids</name>
		<pose>Unspecified</pose>
		<truncated>0</truncated>
		<difficult>0</difficult>
		<bndbox>
			<xmin>95</xmin>
			<ymin>127</ymin>
			<xmax>293</xmax>
			<ymax>365</ymax>
		</bndbox>
	</object>
	<object>
		<name>Aphids</name>
		<pose>Unspecified</pose>
		<truncated>0</truncated>
		<difficult>0</difficult>
		<bndbox>
			<xmin>257</xmin>
			<ymin>173</ymin>
			<xmax>403</xmax>
			<ymax>394</ymax>
		</bndbox>
	</object>
	<object>
		<name>Aphids</name>
		<pose>Unspecified</pose>
		<truncated>0</truncated>
		<difficult>0</difficult>
		<bndbox>
			<xmin>296</xmin>
			<ymin>373</ymin>
			<xmax>480</xmax>
			<ymax>539</ymax>
		</bndbox>
	</object>
	<object>
		<name>Aphids</name>
		<pose>Unspecified</pose>
		<truncated>0</truncated>
		<difficult>0</difficult>
		<bndbox>
			<xmin>170</xmin>
			<ymin>418</ymin>
			<xmax>307</xmax>
			<ymax>552</ymax>
		</bndbox>
	</object>
</annotation>